suno/__init__.py
suno/models.py
suno/suno.py
suno/utils.py
SunoAI-1.0.7.dist-info/LICENSE
SunoAI-1.0.7.dist-info/METADATA
SunoAI-1.0.7.dist-info/WHEEL
SunoAI-1.0.7.dist-info/top_level.txt
SunoAI-1.0.7.dist-info/RECORD
