Metadata-Version: 2.1
Name: SunoAI
Version: 1.0.7
Summary: Python API for interacting with the Suno AI music generator - Unofficial
Home-page: https://github.com/Malith-Rukshan/Suno-API
Author: Malith Rukshan
Author-email: hello@malith.dev
License: MIT
Classifier: Programming Language :: Python :: 3
Classifier: License :: OSI Approved :: MIT License
Requires-Python: >=3.7
License-File: LICENSE
Requires-Dist: requests
Requires-Dist: pydantic
